primeiropacotepypi_10_22/primeiropacotepypi_10_22.py
primeiropacotepypi_10_22-0.0.1.dist-info/LICENSE
primeiropacotepypi_10_22-0.0.1.dist-info/METADATA
primeiropacotepypi_10_22-0.0.1.dist-info/WHEEL
primeiropacotepypi_10_22-0.0.1.dist-info/top_level.txt
primeiropacotepypi_10_22-0.0.1.dist-info/RECORD
