Metadata-Version: 2.1
Name: primeiropacotepypi-10-22
Version: 0.0.1
Summary: Repositório para teste de publicação de pacote no PyPI
Home-page: https://github.com/marco-112358/primeiropacotepypi_10_22
Author: Marco Aurélio
Author-email: marcoaurelioandrade4@gmail.com
License: MIT License
Keywords: Pacote
Platform: UNKNOWN
License-File: LICENSE
Requires-Dist: numpy
